osz2/__init__.py
osz2/__main__.py
osz2/constants.py
osz2/file.py
osz2/keys.py
osz2/metadata.py
osz2/package.py
osz2/patch.py
osz2/simple_cryptor.py
osz2/utils.py
osz2/xtea.py
osz2/xxtea.py
osz2/xxtea_reader.py
osz2-1.0.6.dist-info/licenses/LICENSE
osz2-1.0.6.dist-info/METADATA
osz2-1.0.6.dist-info/WHEEL
osz2-1.0.6.dist-info/entry_points.txt
osz2-1.0.6.dist-info/top_level.txt
osz2-1.0.6.dist-info/RECORD
