Metadata-Version: 2.4
Name: osz2
Version: 1.0.6
Summary: A python library for reading osz2 files
Author: ascenttree
Author-email: Lekuru <contact@lekuru.xyz>
License-Expression: MIT
Project-URL: Homepage, https://github.com/Lekuruu/osz2.py
Keywords: osu,osz2,python,bancho
Requires-Python: >=3.9
License-File: LICENSE
Requires-Dist: numba
Requires-Dist: numpy
Requires-Dist: bsdiff4
Dynamic: license-file
